setup.py
com/__init__.py
com/sg/__init__.py
com/sg/controller/__init__.py
com/sg/controller/test_controller.py
com/sg/test/__init__.py
com/sg/test/tool/Test.py
com/sg/test/tool/__init__.py
com/sg/u/__init__.py
com/sg/u/apiHttp.py
com/sg/u/autoParams.py
com/sg/u/dbUtil.py
com/sg/u/utils.py
sg_auto.egg-info/PKG-INFO
sg_auto.egg-info/SOURCES.txt
sg_auto.egg-info/dependency_links.txt
sg_auto.egg-info/requires.txt
sg_auto.egg-info/top_level.txt